MagViewer
