Metadata-Version: 1.0
Name: magviewer
Version: 0.0.2
Summary: ncl-MAGMOM viewer
Home-page: https://gumijiong.github.io/
Author: GumiJiong
Author-email: Gaomouxu@outlook.com
License: MIT Licence
Keywords: pip,VASP,noncolinear MAGMOM
Platform: any
